ntsc_py/__init__.py
ntsc_py/_library.py
ntsc_py/color.py
ntsc_py/lib_ntsc.cpython-39-darwin.so
ntsc_py/nes_ntsc.py
ntsc_py/sms_ntsc.py
ntsc_py/snes_ntsc.py
ntsc_py/utility.py
ntsc_py-0.2.1.dist-info/LICENSE
ntsc_py-0.2.1.dist-info/METADATA
ntsc_py-0.2.1.dist-info/WHEEL
ntsc_py-0.2.1.dist-info/top_level.txt
ntsc_py-0.2.1.dist-info/RECORD
